DESCRIPTION.rst
MANIFEST.in
README.rst
setup.py
paytrail/__init__.py
paytrail/common.py
paytrail/connectapi.py
paytrail.egg-info/PKG-INFO
paytrail.egg-info/SOURCES.txt
paytrail.egg-info/dependency_links.txt
paytrail.egg-info/top_level.txt