Metadata-Version: 1.1
Name: paytrail
Version: 0.2.1
Summary: Paytrail API libraries
Home-page: https://github.com/paytrail/paytrail
Author: Vesa Kaihlavirta
Author-email: vesa.kaihlavirta@paytrail.com
License: MIT
Keywords: paytrail api connectapi
Platform: UNKNOWN
Classifier: Development Status :: 3 - Alpha
Classifier: Intended Audience :: Developers
Classifier: License :: OSI Approved :: MIT License
Classifier: Programming Language :: Python :: 3
Classifier: Programming Language :: Python :: 3.4
